<?xml version="1.0" encoding="UTF-8"?>
<vivadoHLSLog:LogRoot xmlns:vivadoHLSLog="www.xilinx.com/vivadoHLSLog">
  <errorLogs>
    <logs>
      <csimLog>
        <logs message="ERROR: [SIM 211-100] 'csim_design' failed: compilation error(s)." projectName="hls-project" solutionName="solution1" date="2023-09-25T22:24:09.519+1000"/>
        <logs message="ERROR: [SIM 211-100] 'csim_design' failed: compilation error(s)." projectName="hls-project" solutionName="solution1" date="2023-09-25T22:21:01.875+1000"/>
      </csimLog>
    </logs>
  </errorLogs>
  <warningLogs>
    <logs>
      <csimLog/>
    </logs>
  </warningLogs>
</vivadoHLSLog:LogRoot>
