<?xml version="1.0" encoding="UTF-8"?>
<vivadoHLSLog:LogRoot xmlns:vivadoHLSLog="www.xilinx.com/vivadoHLSLog">
  <errorLogs>
    <logs>
      <synLog/>
    </logs>
  </errorLogs>
  <warningLogs>
    <logs>
      <synLog>
        <logs message="WARNING: [RTGEN 206-101] Design contains AXI ports. Reset is fixed to synchronous and active low." projectName="srcnn_hls" solutionName="solution1" date="2023-11-04T22:07:43.535+1100" type="Warning"/>
        <logs message="WARNING: [RTGEN 206-101] Setting dangling out port 'conv3/grp_fu_428_p_opcode' to 0." projectName="srcnn_hls" solutionName="solution1" date="2023-11-04T22:07:42.184+1100" type="Warning"/>
        <logs message="WARNING: [RTGEN 206-101] Setting dangling out port 'conv3/grp_fu_424_p_opcode' to 0." projectName="srcnn_hls" solutionName="solution1" date="2023-11-04T22:07:42.146+1100" type="Warning"/>
        <logs message="WARNING: [RTGEN 206-101] Setting dangling out port 'conv3/grp_fu_420_p_opcode' to 0." projectName="srcnn_hls" solutionName="solution1" date="2023-11-04T22:07:42.130+1100" type="Warning"/>
        <logs message="WARNING: [RTGEN 206-101] Setting dangling out port 'conv3/grp_fu_416_p_opcode' to 0." projectName="srcnn_hls" solutionName="solution1" date="2023-11-04T22:07:42.116+1100" type="Warning"/>
        <logs message="WARNING: [RTGEN 206-101] Setting dangling out port 'conv3_Pipeline_6/m_axi_o_BREADY' to 0." projectName="srcnn_hls" solutionName="solution1" date="2023-11-04T22:07:40.805+1100" type="Warning"/>
        <logs message="WARNING: [RTGEN 206-101] Setting dangling out port 'conv3_Pipeline_6/m_axi_o_AWUSER' to 0." projectName="srcnn_hls" solutionName="solution1" date="2023-11-04T22:07:40.787+1100" type="Warning"/>
        <logs message="WARNING: [RTGEN 206-101] Setting dangling out port 'conv3_Pipeline_6/m_axi_o_AWREGION' to 0." projectName="srcnn_hls" solutionName="solution1" date="2023-11-04T22:07:40.770+1100" type="Warning"/>
        <logs message="WARNING: [RTGEN 206-101] Setting dangling out port 'conv3_Pipeline_6/m_axi_o_AWQOS' to 0." projectName="srcnn_hls" solutionName="solution1" date="2023-11-04T22:07:40.754+1100" type="Warning"/>
        <logs message="WARNING: [RTGEN 206-101] Setting dangling out port 'conv3_Pipeline_6/m_axi_o_AWPROT' to 0." projectName="srcnn_hls" solutionName="solution1" date="2023-11-04T22:07:40.738+1100" type="Warning"/>
        <logs message="WARNING: [RTGEN 206-101] Setting dangling out port 'conv3_Pipeline_6/m_axi_o_AWCACHE' to 0." projectName="srcnn_hls" solutionName="solution1" date="2023-11-04T22:07:40.720+1100" type="Warning"/>
        <logs message="WARNING: [RTGEN 206-101] Setting dangling out port 'conv3_Pipeline_6/m_axi_o_AWLOCK' to 0." projectName="srcnn_hls" solutionName="solution1" date="2023-11-04T22:07:40.704+1100" type="Warning"/>
        <logs message="WARNING: [RTGEN 206-101] Setting dangling out port 'conv3_Pipeline_6/m_axi_o_AWBURST' to 0." projectName="srcnn_hls" solutionName="solution1" date="2023-11-04T22:07:40.686+1100" type="Warning"/>
        <logs message="WARNING: [RTGEN 206-101] Setting dangling out port 'conv3_Pipeline_6/m_axi_o_AWSIZE' to 0." projectName="srcnn_hls" solutionName="solution1" date="2023-11-04T22:07:40.667+1100" type="Warning"/>
        <logs message="WARNING: [RTGEN 206-101] Setting dangling out port 'conv3_Pipeline_6/m_axi_o_AWLEN' to 0." projectName="srcnn_hls" solutionName="solution1" date="2023-11-04T22:07:40.644+1100" type="Warning"/>
      </synLog>
    </logs>
  </warningLogs>
</vivadoHLSLog:LogRoot>
