<stg><name>conv3_Pipeline_VITIS_LOOP_138_2_VITIS_LOOP_139_3</name>


<trans_list>

<trans id="163" from="1" to="2">
<condition id="-1">
<or_exp><and_exp></and_exp></or_exp>
</condition>
</trans>

<trans id="143" from="2" to="3">
<condition id="-1">
<or_exp><and_exp></and_exp></or_exp>
</condition>
</trans>

<trans id="144" from="3" to="4">
<condition id="-1">
<or_exp><and_exp></and_exp></or_exp>
</condition>
</trans>

<trans id="145" from="4" to="5">
<condition id="-1">
<or_exp><and_exp></and_exp></or_exp>
</condition>
</trans>

<trans id="146" from="5" to="6">
<condition id="-1">
<or_exp><and_exp></and_exp></or_exp>
</condition>
</trans>

<trans id="147" from="6" to="7">
<condition id="-1">
<or_exp><and_exp></and_exp></or_exp>
</condition>
</trans>

<trans id="148" from="7" to="8">
<condition id="-1">
<or_exp><and_exp></and_exp></or_exp>
</condition>
</trans>

<trans id="149" from="8" to="9">
<condition id="-1">
<or_exp><and_exp></and_exp></or_exp>
</condition>
</trans>

<trans id="150" from="9" to="10">
<condition id="-1">
<or_exp><and_exp></and_exp></or_exp>
</condition>
</trans>

<trans id="151" from="10" to="11">
<condition id="-1">
<or_exp><and_exp></and_exp></or_exp>
</condition>
</trans>

<trans id="152" from="11" to="12">
<condition id="-1">
<or_exp><and_exp></and_exp></or_exp>
</condition>
</trans>

<trans id="153" from="12" to="13">
<condition id="-1">
<or_exp><and_exp></and_exp></or_exp>
</condition>
</trans>

<trans id="154" from="13" to="14">
<condition id="-1">
<or_exp><and_exp></and_exp></or_exp>
</condition>
</trans>

<trans id="155" from="14" to="15">
<condition id="-1">
<or_exp><and_exp></and_exp></or_exp>
</condition>
</trans>

<trans id="156" from="15" to="16">
<condition id="-1">
<or_exp><and_exp></and_exp></or_exp>
</condition>
</trans>

<trans id="157" from="16" to="17">
<condition id="-1">
<or_exp><and_exp></and_exp></or_exp>
</condition>
</trans>

<trans id="158" from="17" to="18">
<condition id="-1">
<or_exp><and_exp></and_exp></or_exp>
</condition>
</trans>

<trans id="159" from="18" to="19">
<condition id="-1">
<or_exp><and_exp></and_exp></or_exp>
</condition>
</trans>

<trans id="160" from="19" to="20">
<condition id="-1">
<or_exp><and_exp></and_exp></or_exp>
</condition>
</trans>
</trans_list>



<state_list>

<state id="1" st_id="2">

<operation id="23" st_id="1" stage="1" lat="1">
<core>NULL</core>
<MemPortIdVec></MemPortIdVec>
<condition id="-1">
<or_exp><and_exp></and_exp></or_exp>
</condition>

<Node id="8" bw="5" op_0_bw="32">
<![CDATA[
newFuncRoot:0 %tx = alloca i32 1

]]></Node>
<StgValue><ssdm name="tx"/></StgValue>
</operation>

<operation id="24" st_id="1" stage="1" lat="1">
<core>NULL</core>
<MemPortIdVec></MemPortIdVec>
<condition id="-1">
<or_exp><and_exp></and_exp></or_exp>
</condition>

<Node id="9" bw="5" op_0_bw="32">
<![CDATA[
newFuncRoot:1 %ty = alloca i32 1

]]></Node>
<StgValue><ssdm name="ty"/></StgValue>
</operation>

<operation id="25" st_id="1" stage="1" lat="1">
<core>NULL</core>
<MemPortIdVec></MemPortIdVec>
<condition id="-1">
<or_exp><and_exp></and_exp></or_exp>
</condition>

<Node id="10" bw="9" op_0_bw="32">
<![CDATA[
newFuncRoot:2 %indvar_flatten280 = alloca i32 1

]]></Node>
<StgValue><ssdm name="indvar_flatten280"/></StgValue>
</operation>

<operation id="26" st_id="1" stage="1" lat="1">
<core>NULL</core>
<MemPortIdVec></MemPortIdVec>
<condition id="-1">
<or_exp><and_exp></and_exp></or_exp>
</condition>

<Node id="11" bw="64" op_0_bw="64" op_1_bw="64">
<![CDATA[
newFuncRoot:3 %output_ftmap_read = read i64 @_ssdm_op_Read.ap_auto.i64, i64 %output_ftmap

]]></Node>
<StgValue><ssdm name="output_ftmap_read"/></StgValue>
</operation>

<operation id="27" st_id="1" stage="1" lat="1">
<core>NULL</core>
<MemPortIdVec></MemPortIdVec>
<condition id="-1">
<or_exp><and_exp></and_exp></or_exp>
</condition>

<Node id="12" bw="8" op_0_bw="8" op_1_bw="8">
<![CDATA[
newFuncRoot:4 %p_shl1_read = read i8 @_ssdm_op_Read.ap_auto.i8, i8 %p_shl1

]]></Node>
<StgValue><ssdm name="p_shl1_read"/></StgValue>
</operation>

<operation id="28" st_id="1" stage="1" lat="1">
<core>NULL</core>
<MemPortIdVec></MemPortIdVec>
<condition id="-1">
<or_exp><and_exp></and_exp></or_exp>
</condition>

<Node id="13" bw="4" op_0_bw="4" op_1_bw="4">
<![CDATA[
newFuncRoot:5 %ti_cast20_read = read i4 @_ssdm_op_Read.ap_auto.i4, i4 %ti_cast20

]]></Node>
<StgValue><ssdm name="ti_cast20_read"/></StgValue>
</operation>

<operation id="29" st_id="1" stage="1" lat="1">
<core>NULL</core>
<MemPortIdVec></MemPortIdVec>
<condition id="-1">
<or_exp><and_exp></and_exp></or_exp>
</condition>

<Node id="14" bw="32" op_0_bw="32" op_1_bw="32">
<![CDATA[
newFuncRoot:6 %conv3_biases_0_0_val_read = read i32 @_ssdm_op_Read.ap_auto.float, i32 %conv3_biases_0_0_val

]]></Node>
<StgValue><ssdm name="conv3_biases_0_0_val_read"/></StgValue>
</operation>

<operation id="30" st_id="1" stage="1" lat="1">
<core>NULL</core>
<MemPortIdVec></MemPortIdVec>
<condition id="-1">
<or_exp><and_exp></and_exp></or_exp>
</condition>

<Node id="15" bw="8" op_0_bw="8" op_1_bw="8">
<![CDATA[
newFuncRoot:7 %select_ln31_1_read = read i8 @_ssdm_op_Read.ap_auto.i8, i8 %select_ln31_1

]]></Node>
<StgValue><ssdm name="select_ln31_1_read"/></StgValue>
</operation>

<operation id="31" st_id="1" stage="1" lat="1">
<core>NULL</core>
<MemPortIdVec></MemPortIdVec>
<condition id="-1">
<or_exp><and_exp></and_exp></or_exp>
</condition>

<Node id="16" bw="5" op_0_bw="4">
<![CDATA[
newFuncRoot:8 %ti_cast20_cast = zext i4 %ti_cast20_read

]]></Node>
<StgValue><ssdm name="ti_cast20_cast"/></StgValue>
</operation>

<operation id="32" st_id="1" stage="1" lat="1">
<core>NULL</core>
<MemPortIdVec></MemPortIdVec>
<condition id="-1">
<or_exp><and_exp></and_exp></or_exp>
</condition>

<Node id="17" bw="0" op_0_bw="0" op_1_bw="32" op_2_bw="0" op_3_bw="32" op_4_bw="32" op_5_bw="0" op_6_bw="32" op_7_bw="32" op_8_bw="0" op_9_bw="0" op_10_bw="0" op_11_bw="32" op_12_bw="32" op_13_bw="32" op_14_bw="32" op_15_bw="0" op_16_bw="0" op_17_bw="32" op_18_bw="32">
<![CDATA[
newFuncRoot:9 %specinterface_ln0 = specinterface void @_ssdm_op_SpecInterface, i32 %gmem, void @empty_15, i32 0, i32 0, void @empty_10, i32 0, i32 512, void @empty_19, void @empty_20, void @empty_10, i32 16, i32 16, i32 16, i32 16, void @empty_10, void @empty_10, i32 4294967295, i32 0

]]></Node>
<StgValue><ssdm name="specinterface_ln0"/></StgValue>
</operation>

<operation id="33" st_id="1" stage="1" lat="1">
<core>NULL</core>
<MemPortIdVec></MemPortIdVec>
<condition id="-1">
<or_exp><and_exp></and_exp></or_exp>
</condition>

<Node id="18" bw="0" op_0_bw="9" op_1_bw="9">
<![CDATA[
newFuncRoot:10 %store_ln0 = store i9 0, i9 %indvar_flatten280

]]></Node>
<StgValue><ssdm name="store_ln0"/></StgValue>
</operation>

<operation id="34" st_id="1" stage="1" lat="1">
<core>NULL</core>
<MemPortIdVec></MemPortIdVec>
<condition id="-1">
<or_exp><and_exp></and_exp></or_exp>
</condition>

<Node id="19" bw="0" op_0_bw="5" op_1_bw="5">
<![CDATA[
newFuncRoot:11 %store_ln0 = store i5 0, i5 %ty

]]></Node>
<StgValue><ssdm name="store_ln0"/></StgValue>
</operation>

<operation id="35" st_id="1" stage="1" lat="1">
<core>NULL</core>
<MemPortIdVec></MemPortIdVec>
<condition id="-1">
<or_exp><and_exp></and_exp></or_exp>
</condition>

<Node id="20" bw="0" op_0_bw="5" op_1_bw="5">
<![CDATA[
newFuncRoot:12 %store_ln0 = store i5 0, i5 %tx

]]></Node>
<StgValue><ssdm name="store_ln0"/></StgValue>
</operation>

<operation id="36" st_id="1" stage="1" lat="1">
<core>NULL</core>
<MemPortIdVec></MemPortIdVec>
<condition id="-1">
<or_exp><and_exp></and_exp></or_exp>
</condition>

<Node id="21" bw="0" op_0_bw="0">
<![CDATA[
newFuncRoot:13 %br_ln0 = br void %for.inc.i24

]]></Node>
<StgValue><ssdm name="br_ln0"/></StgValue>
</operation>

<operation id="37" st_id="1" stage="1" lat="1">
<core>NULL</core>
<MemPortIdVec></MemPortIdVec>
<condition id="-1">
<or_exp><and_exp></and_exp></or_exp>
</condition>

<Node id="23" bw="5" op_0_bw="5" op_1_bw="0">
<![CDATA[
for.inc.i24:0 %ty_1 = load i5 %ty

]]></Node>
<StgValue><ssdm name="ty_1"/></StgValue>
</operation>

<operation id="38" st_id="1" stage="1" lat="1">
<core>NULL</core>
<MemPortIdVec></MemPortIdVec>
<condition id="-1">
<or_exp><and_exp></and_exp></or_exp>
</condition>

<Node id="24" bw="9" op_0_bw="9" op_1_bw="0">
<![CDATA[
for.inc.i24:1 %indvar_flatten280_load = load i9 %indvar_flatten280

]]></Node>
<StgValue><ssdm name="indvar_flatten280_load"/></StgValue>
</operation>

<operation id="39" st_id="1" stage="1" lat="1">
<core>NULL</core>
<MemPortIdVec></MemPortIdVec>
<condition id="-1">
<or_exp><and_exp></and_exp></or_exp>
</condition>

<Node id="25" bw="8" op_0_bw="5">
<![CDATA[
for.inc.i24:2 %zext_ln138 = zext i5 %ty_1

]]></Node>
<StgValue><ssdm name="zext_ln138"/></StgValue>
</operation>

<operation id="40" st_id="1" stage="1" lat="1">
<core>Adder</core>
<MemPortIdVec></MemPortIdVec>
<condition id="-1">
<or_exp><and_exp></and_exp></or_exp>
</condition>

<Node id="26" bw="8" op_0_bw="8" op_1_bw="8">
<![CDATA[
for.inc.i24:3 %empty = add i8 %zext_ln138, i8 %select_ln31_1_read

]]></Node>
<StgValue><ssdm name="empty"/></StgValue>
</operation>

<operation id="41" st_id="1" stage="1" lat="1">
<core>NULL</core>
<MemPortIdVec></MemPortIdVec>
<condition id="-1">
<or_exp><and_exp></and_exp></or_exp>
</condition>

<Node id="27" bw="18" op_0_bw="18" op_1_bw="8" op_2_bw="10">
<![CDATA[
for.inc.i24:4 %shl_ln = bitconcatenate i18 @_ssdm_op_BitConcatenate.i18.i8.i10, i8 %empty, i10 0

]]></Node>
<StgValue><ssdm name="shl_ln"/></StgValue>
</operation>

<operation id="42" st_id="1" stage="1" lat="1">
<core>NULL</core>
<MemPortIdVec></MemPortIdVec>
<condition id="-1">
<or_exp><and_exp></and_exp></or_exp>
</condition>

<Node id="28" bw="19" op_0_bw="18">
<![CDATA[
for.inc.i24:5 %zext_ln141 = zext i18 %shl_ln

]]></Node>
<StgValue><ssdm name="zext_ln141"/></StgValue>
</operation>

<operation id="43" st_id="1" stage="1" lat="1">
<core>NULL</core>
<MemPortIdVec></MemPortIdVec>
<condition id="-1">
<or_exp><and_exp></and_exp></or_exp>
</condition>

<Node id="29" bw="10" op_0_bw="10" op_1_bw="8" op_2_bw="2">
<![CDATA[
for.inc.i24:6 %shl_ln141_1 = bitconcatenate i10 @_ssdm_op_BitConcatenate.i10.i8.i2, i8 %empty, i2 0

]]></Node>
<StgValue><ssdm name="shl_ln141_1"/></StgValue>
</operation>

<operation id="44" st_id="1" stage="1" lat="1">
<core>NULL</core>
<MemPortIdVec></MemPortIdVec>
<condition id="-1">
<or_exp><and_exp></and_exp></or_exp>
</condition>

<Node id="30" bw="19" op_0_bw="10">
<![CDATA[
for.inc.i24:7 %zext_ln141_1 = zext i10 %shl_ln141_1

]]></Node>
<StgValue><ssdm name="zext_ln141_1"/></StgValue>
</operation>

<operation id="45" st_id="1" stage="1" lat="1">
<core>Adder</core>
<MemPortIdVec></MemPortIdVec>
<condition id="-1">
<or_exp><and_exp></and_exp></or_exp>
</condition>

<Node id="31" bw="19" op_0_bw="19" op_1_bw="19">
<![CDATA[
for.inc.i24:8 %sub_ln141 = sub i19 %zext_ln141, i19 %zext_ln141_1

]]></Node>
<StgValue><ssdm name="sub_ln141"/></StgValue>
</operation>

<operation id="46" st_id="1" stage="1" lat="1">
<core>NULL</core>
<MemPortIdVec></MemPortIdVec>
<condition id="-1">
<or_exp><and_exp></and_exp></or_exp>
</condition>

<Node id="32" bw="0" op_0_bw="0" op_1_bw="32" op_2_bw="32" op_3_bw="32" op_4_bw="32" op_5_bw="0">
<![CDATA[
for.inc.i24:9 %specpipeline_ln0 = specpipeline void @_ssdm_op_SpecPipeline, i32 4294967295, i32 0, i32 1, i32 0, void @p_str

]]></Node>
<StgValue><ssdm name="specpipeline_ln0"/></StgValue>
</operation>

<operation id="47" st_id="1" stage="1" lat="1">
<core>Cmp</core>
<MemPortIdVec></MemPortIdVec>
<condition id="-1">
<or_exp><and_exp></and_exp></or_exp>
</condition>

<Node id="33" bw="1" op_0_bw="9" op_1_bw="9">
<![CDATA[
for.inc.i24:10 %icmp_ln138 = icmp_eq  i9 %indvar_flatten280_load, i9 289

]]></Node>
<StgValue><ssdm name="icmp_ln138"/></StgValue>
</operation>

<operation id="48" st_id="1" stage="1" lat="1">
<core>Adder</core>
<MemPortIdVec></MemPortIdVec>
<condition id="-1">
<or_exp><and_exp></and_exp></or_exp>
</condition>

<Node id="34" bw="9" op_0_bw="9" op_1_bw="9">
<![CDATA[
for.inc.i24:11 %add_ln138_1 = add i9 %indvar_flatten280_load, i9 1

]]></Node>
<StgValue><ssdm name="add_ln138_1"/></StgValue>
</operation>

<operation id="49" st_id="1" stage="1" lat="1">
<core>NULL</core>
<MemPortIdVec></MemPortIdVec>
<condition id="-1">
<or_exp><and_exp></and_exp></or_exp>
</condition>

<Node id="35" bw="0" op_0_bw="1" op_1_bw="0" op_2_bw="0">
<![CDATA[
for.inc.i24:12 %br_ln138 = br i1 %icmp_ln138, void %for.inc24.i, void %memset.loop.i26.preheader.exitStub

]]></Node>
<StgValue><ssdm name="br_ln138"/></StgValue>
</operation>

<operation id="50" st_id="1" stage="1" lat="1">
<core>NULL</core>
<MemPortIdVec></MemPortIdVec>
<condition id="-1">
<or_exp><and_exp><literal name="icmp_ln138" val="0"/>
</and_exp></or_exp>
</condition>

<Node id="37" bw="5" op_0_bw="5" op_1_bw="0">
<![CDATA[
for.inc24.i:0 %tx_load = load i5 %tx

]]></Node>
<StgValue><ssdm name="tx_load"/></StgValue>
</operation>

<operation id="51" st_id="1" stage="1" lat="1">
<core>Adder</core>
<MemPortIdVec></MemPortIdVec>
<condition id="-1">
<or_exp><and_exp><literal name="icmp_ln138" val="0"/>
</and_exp></or_exp>
</condition>

<Node id="38" bw="5" op_0_bw="5" op_1_bw="5">
<![CDATA[
for.inc24.i:1 %add_ln138 = add i5 %ty_1, i5 1

]]></Node>
<StgValue><ssdm name="add_ln138"/></StgValue>
</operation>

<operation id="52" st_id="1" stage="1" lat="1">
<core>Cmp</core>
<MemPortIdVec></MemPortIdVec>
<condition id="-1">
<or_exp><and_exp><literal name="icmp_ln138" val="0"/>
</and_exp></or_exp>
</condition>

<Node id="41" bw="1" op_0_bw="5" op_1_bw="5">
<![CDATA[
for.inc24.i:4 %icmp_ln139 = icmp_eq  i5 %tx_load, i5 17

]]></Node>
<StgValue><ssdm name="icmp_ln139"/></StgValue>
</operation>

<operation id="53" st_id="1" stage="1" lat="1">
<core>Sel</core>
<MemPortIdVec></MemPortIdVec>
<condition id="-1">
<or_exp><and_exp><literal name="icmp_ln138" val="0"/>
</and_exp></or_exp>
</condition>

<Node id="42" bw="5" op_0_bw="1" op_1_bw="5" op_2_bw="5">
<![CDATA[
for.inc24.i:5 %select_ln138 = select i1 %icmp_ln139, i5 0, i5 %tx_load

]]></Node>
<StgValue><ssdm name="select_ln138"/></StgValue>
</operation>

<operation id="54" st_id="1" stage="1" lat="1">
<core>Sel</core>
<MemPortIdVec></MemPortIdVec>
<condition id="-1">
<or_exp><and_exp><literal name="icmp_ln138" val="0"/>
</and_exp></or_exp>
</condition>

<Node id="43" bw="5" op_0_bw="1" op_1_bw="5" op_2_bw="5">
<![CDATA[
for.inc24.i:6 %select_ln138_1 = select i1 %icmp_ln139, i5 %add_ln138, i5 %ty_1

]]></Node>
<StgValue><ssdm name="select_ln138_1"/></StgValue>
</operation>

<operation id="55" st_id="1" stage="1" lat="1">
<core>NULL</core>
<MemPortIdVec></MemPortIdVec>
<condition id="-1">
<or_exp><and_exp><literal name="icmp_ln138" val="0"/>
</and_exp></or_exp>
</condition>

<Node id="44" bw="9" op_0_bw="5">
<![CDATA[
for.inc24.i:7 %zext_ln141_2 = zext i5 %select_ln138_1

]]></Node>
<StgValue><ssdm name="zext_ln141_2"/></StgValue>
</operation>

<operation id="56" st_id="1" stage="1" lat="1">
<core>NULL</core>
<MemPortIdVec></MemPortIdVec>
<condition id="-1">
<or_exp><and_exp><literal name="icmp_ln138" val="0"/>
</and_exp></or_exp>
</condition>

<Node id="45" bw="9" op_0_bw="9" op_1_bw="5" op_2_bw="4">
<![CDATA[
for.inc24.i:8 %tmp_2 = bitconcatenate i9 @_ssdm_op_BitConcatenate.i9.i5.i4, i5 %select_ln138_1, i4 0

]]></Node>
<StgValue><ssdm name="tmp_2"/></StgValue>
</operation>

<operation id="57" st_id="1" stage="1" lat="1">
<core>TAddSub</core>
<MemPortIdVec></MemPortIdVec>
<condition id="-1">
<or_exp><and_exp><literal name="icmp_ln138" val="0"/>
</and_exp></or_exp>
</condition>

<Node id="46" bw="9" op_0_bw="9" op_1_bw="9">
<![CDATA[
for.inc24.i:9 %add_ln141_4 = add i9 %tmp_2, i9 %zext_ln141_2

]]></Node>
<StgValue><ssdm name="add_ln141_4"/></StgValue>
</operation>

<operation id="58" st_id="1" stage="1" lat="1">
<core>NULL</core>
<MemPortIdVec></MemPortIdVec>
<condition id="-1">
<or_exp><and_exp><literal name="icmp_ln138" val="0"/>
</and_exp></or_exp>
</condition>

<Node id="47" bw="8" op_0_bw="5">
<![CDATA[
for.inc24.i:10 %zext_ln138_1 = zext i5 %add_ln138

]]></Node>
<StgValue><ssdm name="zext_ln138_1"/></StgValue>
</operation>

<operation id="59" st_id="1" stage="1" lat="1">
<core>Adder</core>
<MemPortIdVec></MemPortIdVec>
<condition id="-1">
<or_exp><and_exp><literal name="icmp_ln138" val="0"/>
</and_exp></or_exp>
</condition>

<Node id="48" bw="8" op_0_bw="8" op_1_bw="8">
<![CDATA[
for.inc24.i:11 %p_mid1278 = add i8 %zext_ln138_1, i8 %select_ln31_1_read

]]></Node>
<StgValue><ssdm name="p_mid1278"/></StgValue>
</operation>

<operation id="60" st_id="1" stage="1" lat="1">
<core>NULL</core>
<MemPortIdVec></MemPortIdVec>
<condition id="-1">
<or_exp><and_exp><literal name="icmp_ln138" val="0"/>
</and_exp></or_exp>
</condition>

<Node id="49" bw="18" op_0_bw="18" op_1_bw="8" op_2_bw="10">
<![CDATA[
for.inc24.i:12 %shl_ln141_mid1 = bitconcatenate i18 @_ssdm_op_BitConcatenate.i18.i8.i10, i8 %p_mid1278, i10 0

]]></Node>
<StgValue><ssdm name="shl_ln141_mid1"/></StgValue>
</operation>

<operation id="61" st_id="1" stage="1" lat="1">
<core>NULL</core>
<MemPortIdVec></MemPortIdVec>
<condition id="-1">
<or_exp><and_exp><literal name="icmp_ln138" val="0"/>
</and_exp></or_exp>
</condition>

<Node id="50" bw="19" op_0_bw="18">
<![CDATA[
for.inc24.i:13 %zext_ln141_3 = zext i18 %shl_ln141_mid1

]]></Node>
<StgValue><ssdm name="zext_ln141_3"/></StgValue>
</operation>

<operation id="62" st_id="1" stage="1" lat="1">
<core>NULL</core>
<MemPortIdVec></MemPortIdVec>
<condition id="-1">
<or_exp><and_exp><literal name="icmp_ln138" val="0"/>
</and_exp></or_exp>
</condition>

<Node id="51" bw="10" op_0_bw="10" op_1_bw="8" op_2_bw="2">
<![CDATA[
for.inc24.i:14 %shl_ln141_1_mid1 = bitconcatenate i10 @_ssdm_op_BitConcatenate.i10.i8.i2, i8 %p_mid1278, i2 0

]]></Node>
<StgValue><ssdm name="shl_ln141_1_mid1"/></StgValue>
</operation>

<operation id="63" st_id="1" stage="1" lat="1">
<core>NULL</core>
<MemPortIdVec></MemPortIdVec>
<condition id="-1">
<or_exp><and_exp><literal name="icmp_ln138" val="0"/>
</and_exp></or_exp>
</condition>

<Node id="52" bw="19" op_0_bw="10">
<![CDATA[
for.inc24.i:15 %zext_ln141_5 = zext i10 %shl_ln141_1_mid1

]]></Node>
<StgValue><ssdm name="zext_ln141_5"/></StgValue>
</operation>

<operation id="64" st_id="1" stage="1" lat="1">
<core>Adder</core>
<MemPortIdVec></MemPortIdVec>
<condition id="-1">
<or_exp><and_exp><literal name="icmp_ln138" val="0"/>
</and_exp></or_exp>
</condition>

<Node id="53" bw="19" op_0_bw="19" op_1_bw="19">
<![CDATA[
for.inc24.i:16 %sub_ln141_1 = sub i19 %zext_ln141_3, i19 %zext_ln141_5

]]></Node>
<StgValue><ssdm name="sub_ln141_1"/></StgValue>
</operation>

<operation id="65" st_id="1" stage="1" lat="1">
<core>Sel</core>
<MemPortIdVec></MemPortIdVec>
<condition id="-1">
<or_exp><and_exp><literal name="icmp_ln138" val="0"/>
</and_exp></or_exp>
</condition>

<Node id="54" bw="19" op_0_bw="1" op_1_bw="19" op_2_bw="19">
<![CDATA[
for.inc24.i:17 %select_ln138_2 = select i1 %icmp_ln139, i19 %sub_ln141_1, i19 %sub_ln141

]]></Node>
<StgValue><ssdm name="select_ln138_2"/></StgValue>
</operation>

<operation id="66" st_id="1" stage="1" lat="1">
<core>NULL</core>
<MemPortIdVec></MemPortIdVec>
<condition id="-1">
<or_exp><and_exp><literal name="icmp_ln138" val="0"/>
</and_exp></or_exp>
</condition>

<Node id="55" bw="64" op_0_bw="19">
<![CDATA[
for.inc24.i:18 %sext_ln138 = sext i19 %select_ln138_2

]]></Node>
<StgValue><ssdm name="sext_ln138"/></StgValue>
</operation>

<operation id="67" st_id="1" stage="1" lat="1">
<core>NULL</core>
<MemPortIdVec></MemPortIdVec>
<condition id="-1">
<or_exp><and_exp><literal name="icmp_ln138" val="0"/>
</and_exp></or_exp>
</condition>

<Node id="57" bw="9" op_0_bw="5">
<![CDATA[
for.inc24.i:20 %zext_ln141_7 = zext i5 %select_ln138

]]></Node>
<StgValue><ssdm name="zext_ln141_7"/></StgValue>
</operation>

<operation id="68" st_id="1" stage="1" lat="1">
<core>TAddSub</core>
<MemPortIdVec></MemPortIdVec>
<condition id="-1">
<or_exp><and_exp><literal name="icmp_ln138" val="0"/>
</and_exp></or_exp>
</condition>

<Node id="58" bw="9" op_0_bw="9" op_1_bw="9">
<![CDATA[
for.inc24.i:21 %add_ln141_5 = add i9 %add_ln141_4, i9 %zext_ln141_7

]]></Node>
<StgValue><ssdm name="add_ln141_5"/></StgValue>
</operation>

<operation id="69" st_id="1" stage="1" lat="1">
<core>NULL</core>
<MemPortIdVec></MemPortIdVec>
<condition id="-1">
<or_exp><and_exp><literal name="icmp_ln138" val="0"/>
</and_exp></or_exp>
</condition>

<Node id="59" bw="64" op_0_bw="9">
<![CDATA[
for.inc24.i:22 %zext_ln141_8 = zext i9 %add_ln141_5

]]></Node>
<StgValue><ssdm name="zext_ln141_8"/></StgValue>
</operation>

<operation id="70" st_id="1" stage="1" lat="1">
<core>NULL</core>
<MemPortIdVec></MemPortIdVec>
<condition id="-1">
<or_exp><and_exp><literal name="icmp_ln138" val="0"/>
</and_exp></or_exp>
</condition>

<Node id="60" bw="9" op_0_bw="32" op_1_bw="64" op_2_bw="64">
<![CDATA[
for.inc24.i:23 %output_fm_buffer_0_addr = getelementptr i32 %output_fm_buffer_0, i64 0, i64 %zext_ln141_8

]]></Node>
<StgValue><ssdm name="output_fm_buffer_0_addr"/></StgValue>
</operation>

<operation id="71" st_id="1" stage="2" lat="2">
<core>RAM</core>
<MemPortIdVec></MemPortIdVec>
<condition id="-1">
<or_exp><and_exp><literal name="icmp_ln138" val="0"/>
</and_exp></or_exp>
</condition>

<Node id="62" bw="32" op_0_bw="9">
<![CDATA[
for.inc24.i:25 %output_fm_buffer_0_load = load i9 %output_fm_buffer_0_addr

]]></Node>
<StgValue><ssdm name="output_fm_buffer_0_load"/></StgValue>
</operation>

<operation id="72" st_id="1" stage="1" lat="1">
<core>Adder</core>
<MemPortIdVec></MemPortIdVec>
<condition id="-1">
<or_exp><and_exp><literal name="icmp_ln138" val="0"/>
</and_exp></or_exp>
</condition>

<Node id="64" bw="5" op_0_bw="5" op_1_bw="5">
<![CDATA[
for.inc24.i:27 %add_ln141 = add i5 %ti_cast20_cast, i5 %select_ln138

]]></Node>
<StgValue><ssdm name="add_ln141"/></StgValue>
</operation>

<operation id="73" st_id="1" stage="1" lat="1">
<core>NULL</core>
<MemPortIdVec></MemPortIdVec>
<condition id="-1">
<or_exp><and_exp><literal name="icmp_ln138" val="0"/>
</and_exp></or_exp>
</condition>

<Node id="65" bw="8" op_0_bw="5">
<![CDATA[
for.inc24.i:28 %zext_ln141_4 = zext i5 %add_ln141

]]></Node>
<StgValue><ssdm name="zext_ln141_4"/></StgValue>
</operation>

<operation id="74" st_id="1" stage="1" lat="1">
<core>Adder</core>
<MemPortIdVec></MemPortIdVec>
<condition id="-1">
<or_exp><and_exp><literal name="icmp_ln138" val="0"/>
</and_exp></or_exp>
</condition>

<Node id="66" bw="8" op_0_bw="8" op_1_bw="8">
<![CDATA[
for.inc24.i:29 %add_ln141_1 = add i8 %zext_ln141_4, i8 %p_shl1_read

]]></Node>
<StgValue><ssdm name="add_ln141_1"/></StgValue>
</operation>

<operation id="75" st_id="1" stage="1" lat="1">
<core>NULL</core>
<MemPortIdVec></MemPortIdVec>
<condition id="-1">
<or_exp><and_exp><literal name="icmp_ln138" val="0"/>
</and_exp></or_exp>
</condition>

<Node id="67" bw="10" op_0_bw="10" op_1_bw="8" op_2_bw="2">
<![CDATA[
for.inc24.i:30 %shl_ln141_2 = bitconcatenate i10 @_ssdm_op_BitConcatenate.i10.i8.i2, i8 %add_ln141_1, i2 0

]]></Node>
<StgValue><ssdm name="shl_ln141_2"/></StgValue>
</operation>

<operation id="76" st_id="1" stage="1" lat="1">
<core>NULL</core>
<MemPortIdVec></MemPortIdVec>
<condition id="-1">
<or_exp><and_exp><literal name="icmp_ln138" val="0"/>
</and_exp></or_exp>
</condition>

<Node id="68" bw="64" op_0_bw="10">
<![CDATA[
for.inc24.i:31 %zext_ln141_6 = zext i10 %shl_ln141_2

]]></Node>
<StgValue><ssdm name="zext_ln141_6"/></StgValue>
</operation>

<operation id="77" st_id="1" stage="1" lat="1">
<core>TAddSub</core>
<MemPortIdVec></MemPortIdVec>
<condition id="-1">
<or_exp><and_exp><literal name="icmp_ln138" val="0"/>
</and_exp></or_exp>
</condition>

<Node id="69" bw="64" op_0_bw="64" op_1_bw="64">
<![CDATA[
for.inc24.i:32 %add_ln141_3 = add i64 %zext_ln141_6, i64 %output_ftmap_read

]]></Node>
<StgValue><ssdm name="add_ln141_3"/></StgValue>
</operation>

<operation id="78" st_id="1" stage="1" lat="1">
<core>TAddSub</core>
<MemPortIdVec></MemPortIdVec>
<condition id="-1">
<or_exp><and_exp><literal name="icmp_ln138" val="0"/>
</and_exp></or_exp>
</condition>

<Node id="70" bw="64" op_0_bw="64" op_1_bw="64">
<![CDATA[
for.inc24.i:33 %add_ln141_2 = add i64 %add_ln141_3, i64 %sext_ln138

]]></Node>
<StgValue><ssdm name="add_ln141_2"/></StgValue>
</operation>

<operation id="79" st_id="1" stage="1" lat="1">
<core>NULL</core>
<MemPortIdVec></MemPortIdVec>
<condition id="-1">
<or_exp><and_exp><literal name="icmp_ln138" val="0"/>
</and_exp></or_exp>
</condition>

<Node id="71" bw="62" op_0_bw="62" op_1_bw="64" op_2_bw="32" op_3_bw="32">
<![CDATA[
for.inc24.i:34 %trunc_ln = partselect i62 @_ssdm_op_PartSelect.i62.i64.i32.i32, i64 %add_ln141_2, i32 2, i32 63

]]></Node>
<StgValue><ssdm name="trunc_ln"/></StgValue>
</operation>

<operation id="80" st_id="1" stage="1" lat="1">
<core>NULL</core>
<MemPortIdVec></MemPortIdVec>
<condition id="-1">
<or_exp><and_exp><literal name="icmp_ln138" val="0"/>
</and_exp></or_exp>
</condition>

<Node id="72" bw="64" op_0_bw="62">
<![CDATA[
for.inc24.i:35 %sext_ln141 = sext i62 %trunc_ln

]]></Node>
<StgValue><ssdm name="sext_ln141"/></StgValue>
</operation>

<operation id="81" st_id="1" stage="1" lat="1">
<core>NULL</core>
<MemPortIdVec></MemPortIdVec>
<condition id="-1">
<or_exp><and_exp><literal name="icmp_ln138" val="0"/>
</and_exp></or_exp>
</condition>

<Node id="73" bw="32" op_0_bw="32" op_1_bw="64">
<![CDATA[
for.inc24.i:36 %gmem_addr = getelementptr i32 %gmem, i64 %sext_ln141

]]></Node>
<StgValue><ssdm name="gmem_addr"/></StgValue>
</operation>

<operation id="82" st_id="1" stage="1" lat="1">
<core>NULL</core>
<MemPortIdVec></MemPortIdVec>
<condition id="-1">
<or_exp><and_exp><literal name="icmp_ln138" val="0"/>
</and_exp></or_exp>
</condition>

<Node id="83" bw="0" op_0_bw="9" op_1_bw="9" op_2_bw="0" op_3_bw="0">
<![CDATA[
for.inc24.i:46 %store_ln139 = store i9 %add_ln138_1, i9 %indvar_flatten280

]]></Node>
<StgValue><ssdm name="store_ln139"/></StgValue>
</operation>

<operation id="83" st_id="1" stage="1" lat="1">
<core>NULL</core>
<MemPortIdVec></MemPortIdVec>
<condition id="-1">
<or_exp><and_exp><literal name="icmp_ln138" val="0"/>
</and_exp></or_exp>
</condition>

<Node id="84" bw="0" op_0_bw="5" op_1_bw="5" op_2_bw="0" op_3_bw="0">
<![CDATA[
for.inc24.i:47 %store_ln139 = store i5 %select_ln138_1, i5 %ty

]]></Node>
<StgValue><ssdm name="store_ln139"/></StgValue>
</operation>

<operation id="118" st_id="1" stage="1" lat="1">
<core>NULL</core>
<MemPortIdVec></MemPortIdVec>
<condition id="-1">
<or_exp><and_exp><literal name="icmp_ln138" val="1"/>
</and_exp></or_exp>
</condition>

<Node id="88" bw="0">
<![CDATA[
memset.loop.i26.preheader.exitStub:0 %ret_ln0 = ret

]]></Node>
<StgValue><ssdm name="ret_ln0"/></StgValue>
</operation>
</state>

<state id="2" st_id="3">

<operation id="84" st_id="2" stage="1" lat="2">
<core>RAM</core>
<MemPortIdVec></MemPortIdVec>
<condition id="-1">
<or_exp><and_exp><literal name="icmp_ln138" val="0"/>
</and_exp></or_exp>
</condition>

<Node id="62" bw="32" op_0_bw="9">
<![CDATA[
for.inc24.i:25 %output_fm_buffer_0_load = load i9 %output_fm_buffer_0_addr

]]></Node>
<StgValue><ssdm name="output_fm_buffer_0_load"/></StgValue>
</operation>

<operation id="85" st_id="2" stage="8" lat="8">
<core>m_axi</core>
<MemPortIdVec></MemPortIdVec>
<condition id="-1">
<or_exp><and_exp><literal name="icmp_ln138" val="0"/>
</and_exp></or_exp>
</condition>

<Node id="74" bw="1" op_0_bw="1" op_1_bw="32" op_2_bw="32">
<![CDATA[
for.inc24.i:37 %gmem_load_req = readreq i1 @_ssdm_op_ReadReq.m_axi.i32P1A, i32 %gmem_addr, i32 1

]]></Node>
<StgValue><ssdm name="gmem_load_req"/></StgValue>
</operation>
</state>

<state id="3" st_id="4">

<operation id="86" st_id="3" stage="4" lat="4">
<core>FAddSub_fulldsp</core>
<MemPortIdVec></MemPortIdVec>
<condition id="-1">
<or_exp><and_exp><literal name="icmp_ln138" val="0"/>
</and_exp></or_exp>
</condition>

<Node id="63" bw="32" op_0_bw="32" op_1_bw="32">
<![CDATA[
for.inc24.i:26 %add_i = fadd i32 %output_fm_buffer_0_load, i32 %conv3_biases_0_0_val_read

]]></Node>
<StgValue><ssdm name="add_i"/></StgValue>
</operation>

<operation id="87" st_id="3" stage="7" lat="8">
<core>m_axi</core>
<MemPortIdVec></MemPortIdVec>
<condition id="-1">
<or_exp><and_exp><literal name="icmp_ln138" val="0"/>
</and_exp></or_exp>
</condition>

<Node id="74" bw="1" op_0_bw="1" op_1_bw="32" op_2_bw="32">
<![CDATA[
for.inc24.i:37 %gmem_load_req = readreq i1 @_ssdm_op_ReadReq.m_axi.i32P1A, i32 %gmem_addr, i32 1

]]></Node>
<StgValue><ssdm name="gmem_load_req"/></StgValue>
</operation>
</state>

<state id="4" st_id="5">

<operation id="88" st_id="4" stage="3" lat="4">
<core>FAddSub_fulldsp</core>
<MemPortIdVec></MemPortIdVec>
<condition id="-1">
<or_exp><and_exp><literal name="icmp_ln138" val="0"/>
</and_exp></or_exp>
</condition>

<Node id="63" bw="32" op_0_bw="32" op_1_bw="32">
<![CDATA[
for.inc24.i:26 %add_i = fadd i32 %output_fm_buffer_0_load, i32 %conv3_biases_0_0_val_read

]]></Node>
<StgValue><ssdm name="add_i"/></StgValue>
</operation>

<operation id="89" st_id="4" stage="6" lat="8">
<core>m_axi</core>
<MemPortIdVec></MemPortIdVec>
<condition id="-1">
<or_exp><and_exp><literal name="icmp_ln138" val="0"/>
</and_exp></or_exp>
</condition>

<Node id="74" bw="1" op_0_bw="1" op_1_bw="32" op_2_bw="32">
<![CDATA[
for.inc24.i:37 %gmem_load_req = readreq i1 @_ssdm_op_ReadReq.m_axi.i32P1A, i32 %gmem_addr, i32 1

]]></Node>
<StgValue><ssdm name="gmem_load_req"/></StgValue>
</operation>
</state>

<state id="5" st_id="6">

<operation id="90" st_id="5" stage="2" lat="4">
<core>FAddSub_fulldsp</core>
<MemPortIdVec></MemPortIdVec>
<condition id="-1">
<or_exp><and_exp><literal name="icmp_ln138" val="0"/>
</and_exp></or_exp>
</condition>

<Node id="63" bw="32" op_0_bw="32" op_1_bw="32">
<![CDATA[
for.inc24.i:26 %add_i = fadd i32 %output_fm_buffer_0_load, i32 %conv3_biases_0_0_val_read

]]></Node>
<StgValue><ssdm name="add_i"/></StgValue>
</operation>

<operation id="91" st_id="5" stage="5" lat="8">
<core>m_axi</core>
<MemPortIdVec></MemPortIdVec>
<condition id="-1">
<or_exp><and_exp><literal name="icmp_ln138" val="0"/>
</and_exp></or_exp>
</condition>

<Node id="74" bw="1" op_0_bw="1" op_1_bw="32" op_2_bw="32">
<![CDATA[
for.inc24.i:37 %gmem_load_req = readreq i1 @_ssdm_op_ReadReq.m_axi.i32P1A, i32 %gmem_addr, i32 1

]]></Node>
<StgValue><ssdm name="gmem_load_req"/></StgValue>
</operation>
</state>

<state id="6" st_id="7">

<operation id="92" st_id="6" stage="1" lat="4">
<core>FAddSub_fulldsp</core>
<MemPortIdVec></MemPortIdVec>
<condition id="-1">
<or_exp><and_exp><literal name="icmp_ln138" val="0"/>
</and_exp></or_exp>
</condition>

<Node id="63" bw="32" op_0_bw="32" op_1_bw="32">
<![CDATA[
for.inc24.i:26 %add_i = fadd i32 %output_fm_buffer_0_load, i32 %conv3_biases_0_0_val_read

]]></Node>
<StgValue><ssdm name="add_i"/></StgValue>
</operation>

<operation id="93" st_id="6" stage="4" lat="8">
<core>m_axi</core>
<MemPortIdVec></MemPortIdVec>
<condition id="-1">
<or_exp><and_exp><literal name="icmp_ln138" val="0"/>
</and_exp></or_exp>
</condition>

<Node id="74" bw="1" op_0_bw="1" op_1_bw="32" op_2_bw="32">
<![CDATA[
for.inc24.i:37 %gmem_load_req = readreq i1 @_ssdm_op_ReadReq.m_axi.i32P1A, i32 %gmem_addr, i32 1

]]></Node>
<StgValue><ssdm name="gmem_load_req"/></StgValue>
</operation>
</state>

<state id="7" st_id="8">

<operation id="94" st_id="7" stage="3" lat="8">
<core>m_axi</core>
<MemPortIdVec></MemPortIdVec>
<condition id="-1">
<or_exp><and_exp><literal name="icmp_ln138" val="0"/>
</and_exp></or_exp>
</condition>

<Node id="74" bw="1" op_0_bw="1" op_1_bw="32" op_2_bw="32">
<![CDATA[
for.inc24.i:37 %gmem_load_req = readreq i1 @_ssdm_op_ReadReq.m_axi.i32P1A, i32 %gmem_addr, i32 1

]]></Node>
<StgValue><ssdm name="gmem_load_req"/></StgValue>
</operation>
</state>

<state id="8" st_id="9">

<operation id="95" st_id="8" stage="2" lat="8">
<core>m_axi</core>
<MemPortIdVec></MemPortIdVec>
<condition id="-1">
<or_exp><and_exp><literal name="icmp_ln138" val="0"/>
</and_exp></or_exp>
</condition>

<Node id="74" bw="1" op_0_bw="1" op_1_bw="32" op_2_bw="32">
<![CDATA[
for.inc24.i:37 %gmem_load_req = readreq i1 @_ssdm_op_ReadReq.m_axi.i32P1A, i32 %gmem_addr, i32 1

]]></Node>
<StgValue><ssdm name="gmem_load_req"/></StgValue>
</operation>
</state>

<state id="9" st_id="10">

<operation id="96" st_id="9" stage="1" lat="8">
<core>m_axi</core>
<MemPortIdVec></MemPortIdVec>
<condition id="-1">
<or_exp><and_exp><literal name="icmp_ln138" val="0"/>
</and_exp></or_exp>
</condition>

<Node id="74" bw="1" op_0_bw="1" op_1_bw="32" op_2_bw="32">
<![CDATA[
for.inc24.i:37 %gmem_load_req = readreq i1 @_ssdm_op_ReadReq.m_axi.i32P1A, i32 %gmem_addr, i32 1

]]></Node>
<StgValue><ssdm name="gmem_load_req"/></StgValue>
</operation>
</state>

<state id="10" st_id="11">

<operation id="97" st_id="10" stage="1" lat="1">
<core>m_axi</core>
<MemPortIdVec></MemPortIdVec>
<condition id="-1">
<or_exp><and_exp><literal name="icmp_ln138" val="0"/>
</and_exp></or_exp>
</condition>

<Node id="75" bw="32" op_0_bw="32" op_1_bw="32" op_2_bw="0">
<![CDATA[
for.inc24.i:38 %gmem_addr_read = read i32 @_ssdm_op_Read.m_axi.i32P1A, i32 %gmem_addr

]]></Node>
<StgValue><ssdm name="gmem_addr_read"/></StgValue>
</operation>
</state>

<state id="11" st_id="12">

<operation id="98" st_id="11" stage="1" lat="1">
<core>NULL</core>
<MemPortIdVec></MemPortIdVec>
<condition id="-1">
<or_exp><and_exp><literal name="icmp_ln138" val="0"/>
</and_exp></or_exp>
</condition>

<Node id="76" bw="32" op_0_bw="32">
<![CDATA[
for.inc24.i:39 %bitcast_ln141 = bitcast i32 %gmem_addr_read

]]></Node>
<StgValue><ssdm name="bitcast_ln141"/></StgValue>
</operation>

<operation id="99" st_id="11" stage="4" lat="4">
<core>FAddSub_fulldsp</core>
<MemPortIdVec></MemPortIdVec>
<condition id="-1">
<or_exp><and_exp><literal name="icmp_ln138" val="0"/>
</and_exp></or_exp>
</condition>

<Node id="77" bw="32" op_0_bw="32" op_1_bw="32">
<![CDATA[
for.inc24.i:40 %add23_i = fadd i32 %bitcast_ln141, i32 %add_i

]]></Node>
<StgValue><ssdm name="add23_i"/></StgValue>
</operation>
</state>

<state id="12" st_id="13">

<operation id="100" st_id="12" stage="3" lat="4">
<core>FAddSub_fulldsp</core>
<MemPortIdVec></MemPortIdVec>
<condition id="-1">
<or_exp><and_exp><literal name="icmp_ln138" val="0"/>
</and_exp></or_exp>
</condition>

<Node id="77" bw="32" op_0_bw="32" op_1_bw="32">
<![CDATA[
for.inc24.i:40 %add23_i = fadd i32 %bitcast_ln141, i32 %add_i

]]></Node>
<StgValue><ssdm name="add23_i"/></StgValue>
</operation>
</state>

<state id="13" st_id="14">

<operation id="101" st_id="13" stage="2" lat="4">
<core>FAddSub_fulldsp</core>
<MemPortIdVec></MemPortIdVec>
<condition id="-1">
<or_exp><and_exp><literal name="icmp_ln138" val="0"/>
</and_exp></or_exp>
</condition>

<Node id="77" bw="32" op_0_bw="32" op_1_bw="32">
<![CDATA[
for.inc24.i:40 %add23_i = fadd i32 %bitcast_ln141, i32 %add_i

]]></Node>
<StgValue><ssdm name="add23_i"/></StgValue>
</operation>
</state>

<state id="14" st_id="15">

<operation id="102" st_id="14" stage="1" lat="4">
<core>FAddSub_fulldsp</core>
<MemPortIdVec></MemPortIdVec>
<condition id="-1">
<or_exp><and_exp><literal name="icmp_ln138" val="0"/>
</and_exp></or_exp>
</condition>

<Node id="77" bw="32" op_0_bw="32" op_1_bw="32">
<![CDATA[
for.inc24.i:40 %add23_i = fadd i32 %bitcast_ln141, i32 %add_i

]]></Node>
<StgValue><ssdm name="add23_i"/></StgValue>
</operation>

<operation id="103" st_id="14" stage="1" lat="1">
<core>m_axi</core>
<MemPortIdVec></MemPortIdVec>
<condition id="-1">
<or_exp><and_exp><literal name="icmp_ln138" val="0"/>
</and_exp></or_exp>
</condition>

<Node id="79" bw="1" op_0_bw="1" op_1_bw="32" op_2_bw="32" op_3_bw="0">
<![CDATA[
for.inc24.i:42 %gmem_addr_req = writereq i1 @_ssdm_op_WriteReq.m_axi.i32P1A, i32 %gmem_addr, i32 1

]]></Node>
<StgValue><ssdm name="gmem_addr_req"/></StgValue>
</operation>
</state>

<state id="15" st_id="16">

<operation id="104" st_id="15" stage="1" lat="1">
<core>NULL</core>
<MemPortIdVec></MemPortIdVec>
<condition id="-1">
<or_exp><and_exp><literal name="icmp_ln138" val="0"/>
</and_exp></or_exp>
</condition>

<Node id="78" bw="32" op_0_bw="32">
<![CDATA[
for.inc24.i:41 %bitcast_ln141_1 = bitcast i32 %add23_i

]]></Node>
<StgValue><ssdm name="bitcast_ln141_1"/></StgValue>
</operation>

<operation id="105" st_id="15" stage="1" lat="1">
<core>m_axi</core>
<MemPortIdVec></MemPortIdVec>
<condition id="-1">
<or_exp><and_exp><literal name="icmp_ln138" val="0"/>
</and_exp></or_exp>
</condition>

<Node id="80" bw="0" op_0_bw="0" op_1_bw="32" op_2_bw="32" op_3_bw="4" op_4_bw="0">
<![CDATA[
for.inc24.i:43 %write_ln141 = write void @_ssdm_op_Write.m_axi.i32P1A, i32 %gmem_addr, i32 %bitcast_ln141_1, i4 15

]]></Node>
<StgValue><ssdm name="write_ln141"/></StgValue>
</operation>
</state>

<state id="16" st_id="17">

<operation id="106" st_id="16" stage="5" lat="5">
<core>m_axi</core>
<MemPortIdVec></MemPortIdVec>
<condition id="-1">
<or_exp><and_exp><literal name="icmp_ln138" val="0"/>
</and_exp></or_exp>
</condition>

<Node id="81" bw="1" op_0_bw="1" op_1_bw="32" op_2_bw="0">
<![CDATA[
for.inc24.i:44 %gmem_addr_resp = writeresp i1 @_ssdm_op_WriteResp.m_axi.i32P1A, i32 %gmem_addr

]]></Node>
<StgValue><ssdm name="gmem_addr_resp"/></StgValue>
</operation>
</state>

<state id="17" st_id="18">

<operation id="107" st_id="17" stage="4" lat="5">
<core>m_axi</core>
<MemPortIdVec></MemPortIdVec>
<condition id="-1">
<or_exp><and_exp><literal name="icmp_ln138" val="0"/>
</and_exp></or_exp>
</condition>

<Node id="81" bw="1" op_0_bw="1" op_1_bw="32" op_2_bw="0">
<![CDATA[
for.inc24.i:44 %gmem_addr_resp = writeresp i1 @_ssdm_op_WriteResp.m_axi.i32P1A, i32 %gmem_addr

]]></Node>
<StgValue><ssdm name="gmem_addr_resp"/></StgValue>
</operation>
</state>

<state id="18" st_id="19">

<operation id="108" st_id="18" stage="3" lat="5">
<core>m_axi</core>
<MemPortIdVec></MemPortIdVec>
<condition id="-1">
<or_exp><and_exp><literal name="icmp_ln138" val="0"/>
</and_exp></or_exp>
</condition>

<Node id="81" bw="1" op_0_bw="1" op_1_bw="32" op_2_bw="0">
<![CDATA[
for.inc24.i:44 %gmem_addr_resp = writeresp i1 @_ssdm_op_WriteResp.m_axi.i32P1A, i32 %gmem_addr

]]></Node>
<StgValue><ssdm name="gmem_addr_resp"/></StgValue>
</operation>
</state>

<state id="19" st_id="20">

<operation id="109" st_id="19" stage="2" lat="5">
<core>m_axi</core>
<MemPortIdVec></MemPortIdVec>
<condition id="-1">
<or_exp><and_exp><literal name="icmp_ln138" val="0"/>
</and_exp></or_exp>
</condition>

<Node id="81" bw="1" op_0_bw="1" op_1_bw="32" op_2_bw="0">
<![CDATA[
for.inc24.i:44 %gmem_addr_resp = writeresp i1 @_ssdm_op_WriteResp.m_axi.i32P1A, i32 %gmem_addr

]]></Node>
<StgValue><ssdm name="gmem_addr_resp"/></StgValue>
</operation>

<operation id="110" st_id="19" stage="1" lat="1">
<core>Adder</core>
<MemPortIdVec></MemPortIdVec>
<condition id="-1">
<or_exp><and_exp><literal name="icmp_ln138" val="0"/>
</and_exp></or_exp>
</condition>

<Node id="82" bw="5" op_0_bw="5" op_1_bw="5">
<![CDATA[
for.inc24.i:45 %add_ln139 = add i5 %select_ln138, i5 1

]]></Node>
<StgValue><ssdm name="add_ln139"/></StgValue>
</operation>

<operation id="111" st_id="19" stage="1" lat="1">
<core>NULL</core>
<MemPortIdVec></MemPortIdVec>
<condition id="-1">
<or_exp><and_exp><literal name="icmp_ln138" val="0"/>
</and_exp></or_exp>
</condition>

<Node id="85" bw="0" op_0_bw="5" op_1_bw="5" op_2_bw="0" op_3_bw="0">
<![CDATA[
for.inc24.i:48 %store_ln139 = store i5 %add_ln139, i5 %tx

]]></Node>
<StgValue><ssdm name="store_ln139"/></StgValue>
</operation>
</state>

<state id="20" st_id="21">

<operation id="112" st_id="20" stage="1" lat="1">
<core>NULL</core>
<MemPortIdVec></MemPortIdVec>
<condition id="-1">
<or_exp><and_exp></and_exp></or_exp>
</condition>

<Node id="39" bw="0" op_0_bw="0" op_1_bw="0">
<![CDATA[
for.inc24.i:2 %specloopname_ln0 = specloopname void @_ssdm_op_SpecLoopName, void @VITIS_LOOP_138_2_VITIS_LOOP_139_3_str

]]></Node>
<StgValue><ssdm name="specloopname_ln0"/></StgValue>
</operation>

<operation id="113" st_id="20" stage="1" lat="1">
<core>NULL</core>
<MemPortIdVec></MemPortIdVec>
<condition id="-1">
<or_exp><and_exp></and_exp></or_exp>
</condition>

<Node id="40" bw="0" op_0_bw="0" op_1_bw="64" op_2_bw="64" op_3_bw="64">
<![CDATA[
for.inc24.i:3 %speclooptripcount_ln0 = speclooptripcount void @_ssdm_op_SpecLoopTripCount, i64 289, i64 289, i64 289

]]></Node>
<StgValue><ssdm name="speclooptripcount_ln0"/></StgValue>
</operation>

<operation id="114" st_id="20" stage="1" lat="1">
<core>NULL</core>
<MemPortIdVec></MemPortIdVec>
<condition id="-1">
<or_exp><and_exp></and_exp></or_exp>
</condition>

<Node id="56" bw="0" op_0_bw="0" op_1_bw="32" op_2_bw="32" op_3_bw="32" op_4_bw="32" op_5_bw="0">
<![CDATA[
for.inc24.i:19 %specpipeline_ln0 = specpipeline void @_ssdm_op_SpecPipeline, i32 4294967295, i32 0, i32 1, i32 0, void @p_str

]]></Node>
<StgValue><ssdm name="specpipeline_ln0"/></StgValue>
</operation>

<operation id="115" st_id="20" stage="1" lat="1">
<core>NULL</core>
<MemPortIdVec></MemPortIdVec>
<condition id="-1">
<or_exp><and_exp></and_exp></or_exp>
</condition>

<Node id="61" bw="0" op_0_bw="0" op_1_bw="0">
<![CDATA[
for.inc24.i:24 %specloopname_ln139 = specloopname void @_ssdm_op_SpecLoopName, void @empty_8

]]></Node>
<StgValue><ssdm name="specloopname_ln139"/></StgValue>
</operation>

<operation id="116" st_id="20" stage="1" lat="5">
<core>m_axi</core>
<MemPortIdVec></MemPortIdVec>
<condition id="-1">
<or_exp><and_exp></and_exp></or_exp>
</condition>

<Node id="81" bw="1" op_0_bw="1" op_1_bw="32" op_2_bw="0">
<![CDATA[
for.inc24.i:44 %gmem_addr_resp = writeresp i1 @_ssdm_op_WriteResp.m_axi.i32P1A, i32 %gmem_addr

]]></Node>
<StgValue><ssdm name="gmem_addr_resp"/></StgValue>
</operation>

<operation id="117" st_id="20" stage="1" lat="1">
<core>NULL</core>
<MemPortIdVec></MemPortIdVec>
<condition id="-1">
<or_exp><and_exp></and_exp></or_exp>
</condition>

<Node id="86" bw="0" op_0_bw="0">
<![CDATA[
for.inc24.i:49 %br_ln139 = br void %for.inc.i24

]]></Node>
<StgValue><ssdm name="br_ln139"/></StgValue>
</operation>
</state>
</state_list>


<ports>
</ports>


<dataflows>
</dataflows>


</stg>
